biscuit_auth/__init__.py
biscuit_auth/__init__.pyi
biscuit_auth/biscuit_auth.pypy311-pp73-arm-linux-gnu.so
biscuit_auth/py.typed
biscuit_python-0.4.0.dist-info/METADATA
biscuit_python-0.4.0.dist-info/WHEEL
biscuit_python-0.4.0.dist-info/licenses/LICENSE
biscuit_python-0.4.0.dist-info/RECORD
