Metadata-Version: 2.4
Name: biscuit-python
Version: 0.4.0
License-File: LICENSE
Summary: Python bindings for the biscuit auth platform
Project-URL: homepage, https://biscuitsec.org/usage/python
Project-URL: documentation, https://python.biscuitsec.org
Project-URL: repository, https://github.com/biscuit-auth/biscuit-python
Project-URL: changelog, https://github.com/biscuit-auth/biscuit-python/blob/main/CHANGELOG.md
